PSELPyBaseCamera/__init__.py
PSELPyBaseCamera/__version__.py
PSELPyBaseCamera/helper.py
PSELPyBaseCamera/image_modes.py
PSELPyBaseCamera/logging_tools.py
PSELPyBaseCamera/_abcs_mixins/__init__.py
PSELPyBaseCamera/_abcs_mixins/_abcs_mixins.py
PSELPyBaseCamera/options/__init__.py
PSELPyBaseCamera/options/errors.py
PSELPyBaseCamera/options/results.py
PSELPyBaseCamera/options/types.py
PSELPyBaseCamera-0.2.0.dist-info/LICENSE.txt
PSELPyBaseCamera-0.2.0.dist-info/METADATA
PSELPyBaseCamera-0.2.0.dist-info/WHEEL
PSELPyBaseCamera-0.2.0.dist-info/top_level.txt
PSELPyBaseCamera-0.2.0.dist-info/RECORD
